mary_elizabeth_utils-0.1.26.dist-info/METADATA
mary_elizabeth_utils-0.1.26.dist-info/WHEEL
mary_elizabeth_utils-0.1.26.dist-info/entry_points.txt
mary_elizabeth_utils-0.1.26.dist-info/licenses/LICENSE
mary_elizabeth_utils/config/config.py
mary_elizabeth_utils/config/__init__.py
mary_elizabeth_utils/run.py
mary_elizabeth_utils/analysis/statistics.py
mary_elizabeth_utils/analysis/cohort.py
mary_elizabeth_utils/analysis/__init__.py
mary_elizabeth_utils/_mary_elizabet_utils.pyi
mary_elizabeth_utils/profile_data.py
mary_elizabeth_utils/_version.py
mary_elizabeth_utils/mwx.py
mary_elizabeth_utils/utils/pipeline.py
mary_elizabeth_utils/utils/logger.py
mary_elizabeth_utils/utils/caching.py
mary_elizabeth_utils/utils/reports.py
mary_elizabeth_utils/utils/__init__.py
mary_elizabeth_utils/data/processing.py
mary_elizabeth_utils/data/validation.py
mary_elizabeth_utils/data/loading.py
mary_elizabeth_utils/data/transformation.py
mary_elizabeth_utils/data/__init__.py
mary_elizabeth_utils/data/table_creation.py
mary_elizabeth_utils/icd10.csv
mary_elizabeth_utils/config.yaml
mary_elizabeth_utils/__init__.py
mary_elizabeth_utils/py.typed
mary_elizabeth_utils/main.py
mary_elizabeth_utils/mary_elizabeth_utils.cpython-310-arm-linux-gnueabihf.so
mary_elizabeth_utils-0.1.26.dist-info/RECORD
