Metadata-Version: 2.3
Name: mary-elizabeth-utils
Version: 0.1.26
Classifier: Programming Language :: Python :: 3
Classifier: License :: OSI Approved :: MIT License
Classifier: Operating System :: OS Independent
Requires-Dist: polars
Requires-Dist: matplotlib
Requires-Dist: seaborn
Requires-Dist: pandas
Requires-Dist: numpy
Requires-Dist: colorama
Requires-Dist: pyyaml
Requires-Dist: tqdm
Requires-Dist: pydantic
Requires-Dist: rich
Requires-Dist: python-dateutil
Requires-Dist: pyarrow
Requires-Dist: ydata-profiling
License-File: LICENSE
Summary: My utilities for the different projects
Author-email: Tobias Kragholm <tkragholm@gmail.com>
License: MIT
Requires-Python: >=3.7
